setup.py
bin/mipsy
mipsy/__init__.py
mipsy/arch.py
mipsy/encoder.py
mipsy/util.py
mipsy.egg-info/PKG-INFO
mipsy.egg-info/SOURCES.txt
mipsy.egg-info/dependency_links.txt
mipsy.egg-info/requires.txt
mipsy.egg-info/top_level.txt