Metadata-Version: 1.0
Name: mipsy
Version: 0.1.5
Summary: MIPS32 assembler.
Home-page: https://github.com/ngmiller/mips-assembler
Author: Nick Miller
Author-email: ngmiller@iastate.edu
License: MIT
Platform: UNKNOWN
